{
  "count": 5,
  "results": [
    {
      "shop_section_id": 26730231,
      "title": "Earrings",
      "rank": 1,
      "user_id": 52919634,
      "active_listing_count": 21
    },
    {
      "shop_section_id": 26730425,
      "title": "Pendants",
      "rank": 2,
      "user_id": 52919634,
      "active_listing_count": 19
    },
    {
      "shop_section_id": 26862145,
      "title": "Rings",
      "rank": 3,
      "user_id": 52919634,
      "active_listing_count": 2
    },
    {
      "shop_section_id": 28645842,
      "title": "Pendant and Earring Sets",
      "rank": 4,
      "user_id": 52919634,
      "active_listing_count": 0
    },
    {
      "shop_section_id": 30727640,
      "title": "Nose",
      "rank": 5,
      "user_id": 52919634,
      "active_listing_count": 1
    }
  ]
}
